{
  "MEN": {
    "20260223": {
      "ARKET Canvas Tote Bag": {
        "rank": 1,
        "item_type": "가방",
        "color": "Off White",
        "price": "15,000원"
      },
      "CANYON Regular Boot Cut Jeans": {
        "rank": 4,
        "item_type": "진",
        "color": "Black",
        "price": "169,000원"
      },
      "Relaxed Pinpoint Shirt": {
        "rank": 3,
        "item_type": "셔츠/블라우스",
        "color": "Yellow",
        "price": "129,000원"
      },
      "MIST Wide Jeans": {
        "rank": 5,
        "item_type": "진",
        "color": "Mid Blue",
        "price": "169,000원"
      },
      "Loose-Fit Sweatshirt": {
        "rank": 6,
        "item_type": "스웨트셔츠",
        "color": "Grey Melange",
        "price": "119,000원"
      },
      "Relaxed Long-Sleeve T-Shirt": {
        "rank": 7,
        "item_type": "셔츠/블라우스",
        "color": "Grey-White",
        "price": "79,000원"
      },
      "Waxed Nylon-Cotton Jacket": {
        "rank": 8,
        "item_type": "자켓/블레이저",
        "color": "Black",
        "price": "229,000원"
      },
      "Oversized Oxford Shirt": {
        "rank": 21,
        "item_type": "셔츠/블라우스",
        "color": "Blue-White",
        "price": "129,000원"
      },
      "Cotton Canvas Jacket": {
        "rank": 68,
        "item_type": "자켓/블레이저",
        "color": "Dark Beige",
        "price": "229,000원"
      },
      "Half Zip Polo Shirt": {
        "rank": 11,
        "item_type": "셔츠/블라우스",
        "color": "Faded Blue",
        "price": "129,000원"
      },
      "Relaxed Denim Shirt": {
        "rank": 12,
        "item_type": "셔츠/블라우스",
        "color": "Blue",
        "price": "129,000원"
      },
      "Quilted Liner Jacket": {
        "rank": 13,
        "item_type": "자켓/블레이저",
        "color": "Dark Blue",
        "price": "199,000원"
      },
      "Relaxed Canvas Trousers": {
        "rank": 27,
        "item_type": "팬츠/트라우저",
        "color": "Black",
        "price": "129,000원"
      },
      "Loose Cotton Chinos": {
        "rank": 43,
        "item_type": "팬츠/트라우저",
        "color": "Beige",
        "price": "129,000원"
      },
      "Mid-Weight Sweatshirt": {
        "rank": 33,
        "item_type": "스웨트셔츠",
        "color": "Brown",
        "price": "65,000원"
      },
      "Oversized Poplin Shirt": {
        "rank": 45,
        "item_type": "셔츠/블라우스",
        "color": "Blue-Striped",
        "price": "129,000원"
      },
      "Relaxed Cotton Twill Trousers": {
        "rank": 58,
        "item_type": "팬츠/트라우저",
        "color": "Khaki Green",
        "price": "129,000원"
      },
      "Denim Jacket": {
        "rank": 23,
        "item_type": "자켓/블레이저",
        "color": "Dark Blue",
        "price": "199,000원"
      },
      "Ribbed Cotton Beanie": {
        "rank": 24,
        "item_type": "모자",
        "color": "Black",
        "price": "45,000원"
      },
      "Relaxed Wool Jumper": {
        "rank": 25,
        "item_type": "니트/스웨터",
        "color": "Dark Green",
        "price": "169,000원"
      },
      "Cotton Bouclé Jumper": {
        "rank": 26,
        "item_type": "니트/스웨터",
        "color": "Off White-Dark Blue",
        "price": "149,000원"
      },
      "Chunky Cotton-Blend Polo": {
        "rank": 28,
        "item_type": "폴로",
        "color": "Blue",
        "price": "149,000원"
      },
      "Slim Leather Belt": {
        "rank": 29,
        "item_type": "벨트",
        "color": "Brown",
        "price": "99,000원"
      },
      "Nylon Tote": {
        "rank": 30,
        "item_type": "가방",
        "color": "Black",
        "price": "99,000원"
      },
      "Corduroy Blazer": {
        "rank": 31,
        "item_type": "자켓/블레이저",
        "color": "Dark Blue",
        "price": "279,000원"
      },
      "WCT Sweatshirt": {
        "rank": 32,
        "item_type": "스웨트셔츠",
        "color": "Dark Blue",
        "price": "99,000원"
      },
      "Wool Doublé Jacket": {
        "rank": 34,
        "item_type": "자켓/블레이저",
        "color": "Black",
        "price": "379,000원"
      },
      "Scuba Zip Jacket": {
        "rank": 35,
        "item_type": "자켓/블레이저",
        "color": "Blue",
        "price": "129,000원"
      },
      "Corduroy Overshirt": {
        "rank": 36,
        "item_type": "셔츠/블라우스",
        "color": "Green",
        "price": "169,000원"
      },
      "Cotton Crew-Neck Jumper": {
        "rank": 37,
        "item_type": "니트/스웨터",
        "color": "Beige-Dark Blue",
        "price": "149,000원"
      },
      "Quilted Hood Jacket": {
        "rank": 39,
        "item_type": "자켓/블레이저",
        "color": "Black",
        "price": "229,000원"
      },
      "Cotton Lyocell Polo Shirt": {
        "rank": 40,
        "item_type": "셔츠/블라우스",
        "color": "Green",
        "price": "129,000원"
      },
      "Cotton Cardigan": {
        "rank": 41,
        "item_type": "카디건",
        "color": "Dark Blue",
        "price": "149,000원"
      },
      "2-in-1 Quilted Liner Vest": {
        "rank": 57,
        "item_type": "베스트/조끼",
        "color": "Light Grey",
        "price": "119,000원"
      },
      "OCEAN Loose Straight Jeans": {
        "rank": 71,
        "item_type": "진",
        "color": "Dark Blue",
        "price": "129,000원"
      },
      "Boiled Wool Cardigan": {
        "rank": 46,
        "item_type": "카디건",
        "color": "Brown",
        "price": "169,000원"
      },
      "Indigo Beanie": {
        "rank": 48,
        "item_type": "모자",
        "color": "Blue",
        "price": "55,000원"
      },
      "Loose Fit Cotton Trousers": {
        "rank": 49,
        "item_type": "팬츠/트라우저",
        "color": "Black",
        "price": "149,000원"
      },
      "Corduroy Jacket": {
        "rank": 50,
        "item_type": "자켓/블레이저",
        "color": "Dark Green",
        "price": "199,000원"
      },
      "Relaxed Corduroy Trousers": {
        "rank": 52,
        "item_type": "팬츠/트라우저",
        "color": "Dark Green",
        "price": "149,000원"
      },
      "Fitted Cotton T-Shirt": {
        "rank": 53,
        "item_type": "셔츠/블라우스",
        "color": "Grey",
        "price": "65,000원"
      },
      "Pull-On Trousers": {
        "rank": 55,
        "item_type": "팬츠/트라우저",
        "color": "Dark Grey",
        "price": "149,000원"
      },
      "170 GSM Regular T-Shirt": {
        "rank": 56,
        "item_type": "셔츠/블라우스",
        "color": "Dusty Blue",
        "price": "32,000원"
      },
      "Wool Blend Jacket": {
        "rank": 59,
        "item_type": "자켓/블레이저",
        "color": "Dark Blue",
        "price": "429,000원"
      },
      "Leather Tote": {
        "rank": 60,
        "item_type": "가방",
        "color": "Black",
        "price": "379,000원"
      },
      "36-Hour Tote": {
        "rank": 61,
        "item_type": "가방",
        "color": "Dark Beige",
        "price": "129,000원"
      },
      "Packable Tote": {
        "rank": 62,
        "item_type": "가방",
        "color": "Dark Beige",
        "price": "65,000원"
      },
      "Helmet bag": {
        "rank": 63,
        "item_type": "가방",
        "color": "Khaki Green",
        "price": "169,000원"
      },
      "Relaxed Poplin Shirt": {
        "rank": 64,
        "item_type": "셔츠/블라우스",
        "color": "Light Blue",
        "price": "129,000원"
      },
      "12-Hour Tote-Backpack": {
        "rank": 65,
        "item_type": "가방",
        "color": "Dark Beige",
        "price": "169,000원"
      },
      "Cotton Fleece Long-Sleeve Jumper": {
        "rank": 66,
        "item_type": "니트/스웨터",
        "color": "White-Dark Blue",
        "price": "119,000원"
      },
      "Leather Trainers": {
        "rank": 69,
        "item_type": "미분류",
        "color": "White",
        "price": "259,000원"
      },
      "Braided Leather Trimmed Belt": {
        "rank": 70,
        "item_type": "벨트",
        "color": "Grey",
        "price": "65,000원"
      },
      "Leather Penny Loafers": {
        "rank": 72,
        "item_type": "로퍼",
        "color": "Black",
        "price": "329,000원"
      },
      "Leather Derby Shoes": {
        "rank": 73,
        "item_type": "슈즈",
        "color": "Black",
        "price": "329,000원"
      }
    }
  },
  "WOMEN": {
    "20260223": {
      "Suede-Nylon Trainers": {
        "rank": 25,
        "item_type": "미분류",
        "color": "Dark Brown",
        "price": "169,000원"
      },
      "Pure Cashmere Draped Top": {
        "rank": 2,
        "item_type": "탑",
        "color": "Grey",
        "price": "149,000원"
      },
      "LUPINE Flared Jeans": {
        "rank": 3,
        "item_type": "진",
        "color": "Off White",
        "price": "149,000원"
      },
      "BLOOM Barrel Jeans": {
        "rank": 20,
        "item_type": "진",
        "color": "Blue",
        "price": "149,000원"
      },
      "Wrap-Front Tailored Trousers": {
        "rank": 5,
        "item_type": "팬츠/트라우저",
        "color": "Off White",
        "price": "169,000원"
      },
      "Sculptural Top": {
        "rank": 9,
        "item_type": "탑",
        "color": "Black",
        "price": "99,000원"
      },
      "Knitted Polo Shirt": {
        "rank": 7,
        "item_type": "니트/스웨터",
        "color": "Pink",
        "price": "119,000원"
      },
      "Cargo Trousers": {
        "rank": 10,
        "item_type": "팬츠/트라우저",
        "color": "Brown",
        "price": "149,000원"
      },
      "LILY Signature T-Shirt": {
        "rank": 24,
        "item_type": "셔츠/블라우스",
        "color": "Pink-Purple",
        "price": "32,000원"
      },
      "Oversized Trench Jacket": {
        "rank": 12,
        "item_type": "자켓/블레이저",
        "color": "Black",
        "price": "279,000원"
      },
      "Bubble-Hem Jacket": {
        "rank": 13,
        "item_type": "자켓/블레이저",
        "color": "Light Beige",
        "price": "149,000원"
      },
      "Cotton Shirt": {
        "rank": 31,
        "item_type": "셔츠/블라우스",
        "color": "Brown-White",
        "price": "129,000원"
      },
      "Lined Canvas Jacket": {
        "rank": 16,
        "item_type": "자켓/블레이저",
        "color": "Pink",
        "price": "279,000원"
      },
      "Wool Polo Jumper": {
        "rank": 17,
        "item_type": "니트/스웨터",
        "color": "Brown-Grey-Pink",
        "price": "129,000원"
      },
      "Alpaca-Wool Blend Jumper": {
        "rank": 18,
        "item_type": "니트/스웨터",
        "color": "Light Mole",
        "price": "129,000원"
      },
      "Peep-Toe Pumps": {
        "rank": 19,
        "item_type": "미분류",
        "color": "Black",
        "price": "259,000원"
      },
      "Curved Slit Shirt": {
        "rank": 34,
        "item_type": "셔츠/블라우스",
        "color": "Blue",
        "price": "129,000원"
      },
      "Barrel-Leg Jeans": {
        "rank": 40,
        "item_type": "진",
        "color": "Dark Blue",
        "price": "169,000원"
      },
      "Relaxed Stand-Collar Shirt": {
        "rank": 23,
        "item_type": "셔츠/블라우스",
        "color": "White",
        "price": "149,000원"
      },
      "PEARL Heavyweight T-Shirt": {
        "rank": 26,
        "item_type": "셔츠/블라우스",
        "color": "Blue",
        "price": "55,000원"
      },
      "Tailored Side-Slit Trousers": {
        "rank": 42,
        "item_type": "팬츠/트라우저",
        "color": "Red",
        "price": "199,000원"
      },
      "V-Neck Sweatshirt": {
        "rank": 28,
        "item_type": "스웨트셔츠",
        "color": "Grey Melange",
        "price": "119,000원"
      },
      "Wool-Blend Doublé Jacket": {
        "rank": 35,
        "item_type": "자켓/블레이저",
        "color": "Beige",
        "price": "399,000원"
      },
      "Ribbed Wrap Top": {
        "rank": 36,
        "item_type": "탑",
        "color": "Dark Brown",
        "price": "149,000원"
      },
      "CORAL Wide Jeans": {
        "rank": 32,
        "item_type": "진",
        "color": "Off White",
        "price": "169,000원"
      },
      "Fluid Cargo Trousers": {
        "rank": 33,
        "item_type": "팬츠/트라우저",
        "color": "Black",
        "price": "149,000원"
      },
      "Terry Sweatshirt": {
        "rank": 37,
        "item_type": "스웨트셔츠",
        "color": "Brown",
        "price": "79,000원"
      },
      "Mini Bubble Skirt": {
        "rank": 38,
        "item_type": "스커트",
        "color": "Brown",
        "price": "129,000원"
      },
      "Sculptural Leather Jacket": {
        "rank": 39,
        "item_type": "자켓/블레이저",
        "color": "Black",
        "price": "799,000원"
      },
      "Suede Ballerina": {
        "rank": 41,
        "item_type": "미분류",
        "color": "Brown",
        "price": "229,000원"
      },
      "Double-Breasted Blazer": {
        "rank": 43,
        "item_type": "자켓/블레이저",
        "color": "Off White",
        "price": "479,000원"
      },
      "Slouchy Leather Bag": {
        "rank": 44,
        "item_type": "가방",
        "color": "Brown",
        "price": "259,000원"
      },
      "Pony Hair-Effect Ballerinas": {
        "rank": 45,
        "item_type": "미분류",
        "color": "Beige-Black-Faux Zebra",
        "price": "169,000원"
      },
      "Balloon-Hem T-Shirt": {
        "rank": 46,
        "item_type": "셔츠/블라우스",
        "color": "Off White",
        "price": "99,000원"
      },
      "Zebra-Print Leather Belt": {
        "rank": 47,
        "item_type": "벨트",
        "color": "White-Black-Faux Zebra",
        "price": "119,000원"
      },
      "Clear Glass Cuff Bracelet": {
        "rank": 48,
        "item_type": "주얼리",
        "color": "Clear",
        "price": "65,000원"
      },
      "Barrel-Shaped Cotton Skirt": {
        "rank": 49,
        "item_type": "스커트",
        "color": "Red",
        "price": "149,000원"
      },
      "Draped Pleated Trousers": {
        "rank": 50,
        "item_type": "팬츠/트라우저",
        "color": "Pink",
        "price": "199,000원"
      },
      "Suede Crossbody Bag": {
        "rank": 70,
        "item_type": "가방",
        "color": "Black",
        "price": "229,000원"
      },
      "Cotton-Silk Shirt": {
        "rank": 52,
        "item_type": "셔츠/블라우스",
        "color": "Beige",
        "price": "169,000원"
      },
      "Zip Jacket": {
        "rank": 53,
        "item_type": "자켓/블레이저",
        "color": "Dark Brown",
        "price": "279,000원"
      },
      "Balloon Light Jacket": {
        "rank": 54,
        "item_type": "자켓/블레이저",
        "color": "Cream",
        "price": "129,000원"
      },
      "Suede Pouch": {
        "rank": 55,
        "item_type": "미분류",
        "color": "Black",
        "price": "229,000원"
      },
      "Printed Silk Scarf": {
        "rank": 56,
        "item_type": "스카프/머플러",
        "color": "Beige-Black",
        "price": "79,000원"
      },
      "Merino Wool Roll-Neck Jumper": {
        "rank": 57,
        "item_type": "니트/스웨터",
        "color": "Black",
        "price": "129,000원"
      },
      "Shirt-Detail Long-Sleeve T-Shirt": {
        "rank": 58,
        "item_type": "셔츠/블라우스",
        "color": "Light Pink",
        "price": "119,000원"
      },
      "Tailored Waistcoat": {
        "rank": 59,
        "item_type": "코트",
        "color": "Dark Beige",
        "price": "169,000원"
      },
      "Open-Neck Blouse": {
        "rank": 60,
        "item_type": "셔츠/블라우스",
        "color": "Blue",
        "price": "129,000원"
      },
      "Doublé Wool-Blend Blazer": {
        "rank": 61,
        "item_type": "자켓/블레이저",
        "color": "Brown",
        "price": "329,000원"
      },
      "Jacquard Jacket": {
        "rank": 62,
        "item_type": "자켓/블레이저",
        "color": "Beige-Black",
        "price": "399,000원"
      },
      "Scarf Trench Coat": {
        "rank": 63,
        "item_type": "코트",
        "color": "Beige",
        "price": "429,000원"
      },
      "Wide Tailored Trousers": {
        "rank": 64,
        "item_type": "팬츠/트라우저",
        "color": "Dark Beige",
        "price": "199,000원"
      },
      "Barrel-Leg Trousers": {
        "rank": 65,
        "item_type": "팬츠/트라우저",
        "color": "Black",
        "price": "199,000원"
      },
      "Clip-On Earrings": {
        "rank": 66,
        "item_type": "주얼리",
        "color": "White-Clear",
        "price": "65,000원"
      },
      "Cashmere-Wool Polo Jumper": {
        "rank": 67,
        "item_type": "니트/스웨터",
        "color": "Beige",
        "price": "229,000원"
      },
      "Barrel-Leg Corduroy Trousers": {
        "rank": 68,
        "item_type": "팬츠/트라우저",
        "color": "Dark Brown",
        "price": "149,000원"
      },
      "Leather Loafers": {
        "rank": 69,
        "item_type": "로퍼",
        "color": "Dark Red",
        "price": "379,000원"
      },
      "Suede Trainers": {
        "rank": 71,
        "item_type": "미분류",
        "color": "Dark Brown-Faux Snake",
        "price": "259,000원"
      },
      "Zebra-Print Leather Crossbody Bag": {
        "rank": 72,
        "item_type": "가방",
        "color": "Black-White-Faux Zebra",
        "price": "199,000원"
      }
    }
  }
}